[{"id":"220283103001","code":"220283103001","name":"朝阳社区","parentCode":"220283103","level":5,"center":null,"hasChildren":false},{"id":"220283103200","code":"220283103200","name":"新旭村","parentCode":"220283103","level":5,"center":null,"hasChildren":false},{"id":"220283103201","code":"220283103201","name":"兴安村","parentCode":"220283103","level":5,"center":null,"hasChildren":false},{"id":"220283103202","code":"220283103202","name":"永合村","parentCode":"220283103","level":5,"center":null,"hasChildren":false},{"id":"220283103203","code":"220283103203","name":"富民村","parentCode":"220283103","level":5,"center":null,"hasChildren":false},{"id":"220283103204","code":"220283103204","name":"合兴村","parentCode":"220283103","level":5,"center":null,"hasChildren":false},{"id":"220283103205","code":"220283103205","name":"东胜村","parentCode":"220283103","level":5,"center":null,"hasChildren":false},{"id":"220283103206","code":"220283103206","name":"恒林村","parentCode":"220283103","level":5,"center":null,"hasChildren":false},{"id":"220283103207","code":"220283103207","name":"双兴村","parentCode":"220283103","level":5,"center":null,"hasChildren":false}]
