[{"id":"350212005001","code":"350212005001","name":"西洪塘社区居委会","parentCode":"350212005","level":5,"center":null,"hasChildren":false},{"id":"350212005002","code":"350212005002","name":"西湖社区居委会","parentCode":"350212005","level":5,"center":null,"hasChildren":false},{"id":"350212005003","code":"350212005003","name":"阳翟社区居委会","parentCode":"350212005","level":5,"center":null,"hasChildren":false},{"id":"350212005004","code":"350212005004","name":"祥晖社区居委会","parentCode":"350212005","level":5,"center":null,"hasChildren":false},{"id":"350212005005","code":"350212005005","name":"祥文社区居委会","parentCode":"350212005","level":5,"center":null,"hasChildren":false},{"id":"350212005006","code":"350212005006","name":"祥丰社区居委会","parentCode":"350212005","level":5,"center":null,"hasChildren":false},{"id":"350212005201","code":"350212005201","name":"卿朴村委会","parentCode":"350212005","level":5,"center":null,"hasChildren":false},{"id":"350212005202","code":"350212005202","name":"瑶头村委会","parentCode":"350212005","level":5,"center":null,"hasChildren":false}]
