[{"id":"370202004001","code":"370202004001","name":"寿张路社区","parentCode":"370202004","level":5,"center":null,"hasChildren":false},{"id":"370202004005","code":"370202004005","name":"四川路社区","parentCode":"370202004","level":5,"center":null,"hasChildren":false},{"id":"370202004013","code":"370202004013","name":"广州路社区","parentCode":"370202004","level":5,"center":null,"hasChildren":false},{"id":"370202004014","code":"370202004014","name":"云南路社区","parentCode":"370202004","level":5,"center":null,"hasChildren":false}]
