[{"id":"371622107215","code":"371622107215","name":"崔寨村村民委员会","parentCode":"371622107","level":5,"center":null,"hasChildren":false},{"id":"371622107263","code":"371622107263","name":"大王村村民委员会","parentCode":"371622107","level":5,"center":null,"hasChildren":false},{"id":"371622107265","code":"371622107265","name":"鞭子侯村村民委员会","parentCode":"371622107","level":5,"center":null,"hasChildren":false},{"id":"371622107281","code":"371622107281","name":"司家村村民委员会","parentCode":"371622107","level":5,"center":null,"hasChildren":false},{"id":"371622107283","code":"371622107283","name":"欧李村村民委员会","parentCode":"371622107","level":5,"center":null,"hasChildren":false},{"id":"371622107286","code":"371622107286","name":"振兴村","parentCode":"371622107","level":5,"center":null,"hasChildren":false},{"id":"371622107287","code":"371622107287","name":"新香村","parentCode":"371622107","level":5,"center":null,"hasChildren":false},{"id":"371622107288","code":"371622107288","name":"劳店新村","parentCode":"371622107","level":5,"center":null,"hasChildren":false},{"id":"371622107289","code":"371622107289","name":"王曹新村","parentCode":"371622107","level":5,"center":null,"hasChildren":false},{"id":"371622107290","code":"371622107290","name":"幸福新村","parentCode":"371622107","level":5,"center":null,"hasChildren":false},{"id":"371622107291","code":"371622107291","name":"毛家寨村","parentCode":"371622107","level":5,"center":null,"hasChildren":false},{"id":"371622107292","code":"371622107292","name":"皂杨村","parentCode":"371622107","level":5,"center":null,"hasChildren":false},{"id":"371622107293","code":"371622107293","name":"大庄村","parentCode":"371622107","level":5,"center":null,"hasChildren":false},{"id":"371622107294","code":"371622107294","name":"东风村","parentCode":"371622107","level":5,"center":null,"hasChildren":false},{"id":"371622107295","code":"371622107295","name":"向阳村","parentCode":"371622107","level":5,"center":null,"hasChildren":false},{"id":"371622107296","code":"371622107296","name":"东盛村","parentCode":"371622107","level":5,"center":null,"hasChildren":false},{"id":"371622107297","code":"371622107297","name":"永兴村","parentCode":"371622107","level":5,"center":null,"hasChildren":false},{"id":"371622107298","code":"371622107298","name":"永安村","parentCode":"371622107","level":5,"center":null,"hasChildren":false},{"id":"371622107299","code":"371622107299","name":"瑞祥村","parentCode":"371622107","level":5,"center":null,"hasChildren":false},{"id":"371622107300","code":"371622107300","name":"祥和村","parentCode":"371622107","level":5,"center":null,"hasChildren":false},{"id":"371622107301","code":"371622107301","name":"兴旺村","parentCode":"371622107","level":5,"center":null,"hasChildren":false},{"id":"371622107302","code":"371622107302","name":"幸福里村","parentCode":"371622107","level":5,"center":null,"hasChildren":false},{"id":"371622107303","code":"371622107303","name":"建国新村","parentCode":"371622107","level":5,"center":null,"hasChildren":false},{"id":"371622107304","code":"371622107304","name":"新陈楼村","parentCode":"371622107","level":5,"center":null,"hasChildren":false},{"id":"371622107305","code":"371622107305","name":"新华村","parentCode":"371622107","level":5,"center":null,"hasChildren":false},{"id":"371622107306","code":"371622107306","name":"秃李村","parentCode":"371622107","level":5,"center":null,"hasChildren":false},{"id":"371622107307","code":"371622107307","name":"兴隆村","parentCode":"371622107","level":5,"center":null,"hasChildren":false},{"id":"371622107308","code":"371622107308","name":"前周张乔村","parentCode":"371622107","level":5,"center":null,"hasChildren":false},{"id":"371622107309","code":"371622107309","name":"北朱村村民委员会","parentCode":"371622107","level":5,"center":null,"hasChildren":false},{"id":"371622107310","code":"371622107310","name":"果刘付村","parentCode":"371622107","level":5,"center":null,"hasChildren":false},{"id":"371622107311","code":"371622107311","name":"兴安村","parentCode":"371622107","level":5,"center":null,"hasChildren":false},{"id":"371622107312","code":"371622107312","name":"东升村","parentCode":"371622107","level":5,"center":null,"hasChildren":false},{"id":"371622107313","code":"371622107313","name":"湖畔家园村","parentCode":"371622107","level":5,"center":null,"hasChildren":false},{"id":"371622107314","code":"371622107314","name":"双井村","parentCode":"371622107","level":5,"center":null,"hasChildren":false}]
