[{"id":"411424001","code":"411424001","name":"凤凰街道","parentCode":"411424","level":4,"center":null,"hasChildren":true},{"id":"411424002","code":"411424002","name":"浦东街道","parentCode":"411424","level":4,"center":null,"hasChildren":true},{"id":"411424003","code":"411424003","name":"春水街道","parentCode":"411424","level":4,"center":null,"hasChildren":true},{"id":"411424004","code":"411424004","name":"双河街道","parentCode":"411424","level":4,"center":null,"hasChildren":true},{"id":"411424101","code":"411424101","name":"陈青集镇","parentCode":"411424","level":4,"center":null,"hasChildren":true},{"id":"411424102","code":"411424102","name":"起台镇","parentCode":"411424","level":4,"center":null,"hasChildren":true},{"id":"411424103","code":"411424103","name":"胡襄镇","parentCode":"411424","level":4,"center":null,"hasChildren":true},{"id":"411424104","code":"411424104","name":"慈圣镇","parentCode":"411424","level":4,"center":null,"hasChildren":true},{"id":"411424105","code":"411424105","name":"安平镇","parentCode":"411424","level":4,"center":null,"hasChildren":true},{"id":"411424106","code":"411424106","name":"远襄镇","parentCode":"411424","level":4,"center":null,"hasChildren":true},{"id":"411424107","code":"411424107","name":"岗王镇","parentCode":"411424","level":4,"center":null,"hasChildren":true},{"id":"411424108","code":"411424108","name":"伯岗镇","parentCode":"411424","level":4,"center":null,"hasChildren":true},{"id":"411424109","code":"411424109","name":"张桥镇","parentCode":"411424","level":4,"center":null,"hasChildren":true},{"id":"411424110","code":"411424110","name":"老王集镇","parentCode":"411424","level":4,"center":null,"hasChildren":true},{"id":"411424111","code":"411424111","name":"朱襄镇","parentCode":"411424","level":4,"center":null,"hasChildren":true},{"id":"411424203","code":"411424203","name":"洪恩乡","parentCode":"411424","level":4,"center":null,"hasChildren":true},{"id":"411424206","code":"411424206","name":"马集乡","parentCode":"411424","level":4,"center":null,"hasChildren":true},{"id":"411424207","code":"411424207","name":"牛城乡","parentCode":"411424","level":4,"center":null,"hasChildren":true},{"id":"411424208","code":"411424208","name":"惠济乡","parentCode":"411424","level":4,"center":null,"hasChildren":true},{"id":"411424212","code":"411424212","name":"申桥乡","parentCode":"411424","level":4,"center":null,"hasChildren":true},{"id":"411424213","code":"411424213","name":"李原乡","parentCode":"411424","level":4,"center":null,"hasChildren":true},{"id":"411424214","code":"411424214","name":"皇集乡","parentCode":"411424","level":4,"center":null,"hasChildren":true}]
