[{"id":"420502009002","code":"420502009002","name":"东山花园社区居委会","parentCode":"420502009","level":5,"center":null,"hasChildren":false},{"id":"420502009004","code":"420502009004","name":"城东社区居委会","parentCode":"420502009","level":5,"center":null,"hasChildren":false},{"id":"420502009005","code":"420502009005","name":"廖家湾社区居委会","parentCode":"420502009","level":5,"center":null,"hasChildren":false},{"id":"420502009006","code":"420502009006","name":"叶家坝社区居委会","parentCode":"420502009","level":5,"center":null,"hasChildren":false},{"id":"420502009201","code":"420502009201","name":"张家村委会","parentCode":"420502009","level":5,"center":null,"hasChildren":false}]
