[{"id":"511528107004","code":"511528107004","name":"僰城社区居民委员会","parentCode":"511528107","level":5,"center":null,"hasChildren":false},{"id":"511528107202","code":"511528107202","name":"建武村民委员会","parentCode":"511528107","level":5,"center":null,"hasChildren":false},{"id":"511528107206","code":"511528107206","name":"九丝村民委员会","parentCode":"511528107","level":5,"center":null,"hasChildren":false},{"id":"511528107209","code":"511528107209","name":"新丰村民委员会","parentCode":"511528107","level":5,"center":null,"hasChildren":false},{"id":"511528107215","code":"511528107215","name":"坪山村民委员会","parentCode":"511528107","level":5,"center":null,"hasChildren":false},{"id":"511528107219","code":"511528107219","name":"文印村民委员会","parentCode":"511528107","level":5,"center":null,"hasChildren":false},{"id":"511528107226","code":"511528107226","name":"新合村民委员会","parentCode":"511528107","level":5,"center":null,"hasChildren":false},{"id":"511528107227","code":"511528107227","name":"簸峡村民委员会","parentCode":"511528107","level":5,"center":null,"hasChildren":false},{"id":"511528107229","code":"511528107229","name":"红胜堰村民委员会","parentCode":"511528107","level":5,"center":null,"hasChildren":false},{"id":"511528107230","code":"511528107230","name":"文山村民委员会","parentCode":"511528107","level":5,"center":null,"hasChildren":false},{"id":"511528107231","code":"511528107231","name":"迎春村民委员会","parentCode":"511528107","level":5,"center":null,"hasChildren":false},{"id":"511528107232","code":"511528107232","name":"和新村民委员会","parentCode":"511528107","level":5,"center":null,"hasChildren":false},{"id":"511528107233","code":"511528107233","name":"胜利村民委员会","parentCode":"511528107","level":5,"center":null,"hasChildren":false},{"id":"511528107234","code":"511528107234","name":"惠源村民委员会","parentCode":"511528107","level":5,"center":null,"hasChildren":false},{"id":"511528107235","code":"511528107235","name":"鲵源村民委员会","parentCode":"511528107","level":5,"center":null,"hasChildren":false}]
