[{"id":"530102010001","code":"530102010001","name":"东村社区居民委员会","parentCode":"530102010","level":5,"center":null,"hasChildren":false},{"id":"530102010002","code":"530102010002","name":"大村社区居民委员会","parentCode":"530102010","level":5,"center":null,"hasChildren":false},{"id":"530102010003","code":"530102010003","name":"桃园社区居民委员会","parentCode":"530102010","level":5,"center":null,"hasChildren":false},{"id":"530102010004","code":"530102010004","name":"三多社区居民委员会","parentCode":"530102010","level":5,"center":null,"hasChildren":false},{"id":"530102010005","code":"530102010005","name":"龙庆社区居民委员会","parentCode":"530102010","level":5,"center":null,"hasChildren":false},{"id":"530102010006","code":"530102010006","name":"陡坡社区居民委员会","parentCode":"530102010","level":5,"center":null,"hasChildren":false},{"id":"530102010007","code":"530102010007","name":"新民社区居民委员会","parentCode":"530102010","level":5,"center":null,"hasChildren":false},{"id":"530102010008","code":"530102010008","name":"陡普鲁社区居民委员会","parentCode":"530102010","level":5,"center":null,"hasChildren":false},{"id":"530102010009","code":"530102010009","name":"厂口社区居民委员会","parentCode":"530102010","level":5,"center":null,"hasChildren":false},{"id":"530102010010","code":"530102010010","name":"迤六社区居民委员会","parentCode":"530102010","level":5,"center":null,"hasChildren":false},{"id":"530102010011","code":"530102010011","name":"瓦恭社区居民委员会","parentCode":"530102010","level":5,"center":null,"hasChildren":false}]
