[{"id":"632524100","code":"632524100","name":"子科滩镇","parentCode":"632524","level":4,"center":null,"hasChildren":true},{"id":"632524101","code":"632524101","name":"河卡镇","parentCode":"632524","level":4,"center":null,"hasChildren":true},{"id":"632524102","code":"632524102","name":"曲什安镇","parentCode":"632524","level":4,"center":null,"hasChildren":true},{"id":"632524200","code":"632524200","name":"温泉乡","parentCode":"632524","level":4,"center":null,"hasChildren":true},{"id":"632524201","code":"632524201","name":"龙藏乡","parentCode":"632524","level":4,"center":null,"hasChildren":true},{"id":"632524202","code":"632524202","name":"中铁乡","parentCode":"632524","level":4,"center":null,"hasChildren":true},{"id":"632524203","code":"632524203","name":"唐乃亥乡","parentCode":"632524","level":4,"center":null,"hasChildren":true}]
