[{"id":"652801207001","code":"652801207001","name":"湖滨社区居委会","parentCode":"652801207","level":5,"center":null,"hasChildren":false},{"id":"652801207200","code":"652801207200","name":"托布力其村委会","parentCode":"652801207","level":5,"center":null,"hasChildren":false},{"id":"652801207201","code":"652801207201","name":"上牙克托格拉克村委会","parentCode":"652801207","level":5,"center":null,"hasChildren":false},{"id":"652801207202","code":"652801207202","name":"下牙克托格拉克村委会","parentCode":"652801207","level":5,"center":null,"hasChildren":false},{"id":"652801207203","code":"652801207203","name":"新村","parentCode":"652801207","level":5,"center":null,"hasChildren":false},{"id":"652801207204","code":"652801207204","name":"艾力坎土曼村委会","parentCode":"652801207","level":5,"center":null,"hasChildren":false}]
